setup.py
geolocation/__init__.py
geolocation/api.py
geolocation/const.py
geolocation/google_maps.py
geolocation/models.py
geolocation/parsers.py
geolocation_python.egg-info/PKG-INFO
geolocation_python.egg-info/SOURCES.txt
geolocation_python.egg-info/dependency_links.txt
geolocation_python.egg-info/requires.txt
geolocation_python.egg-info/top_level.txt