Metadata-Version: 1.1
Name: geolocation-python
Version: 0.1.2b
Summary: Geolocation is a simple and clever application which uses google maps api. This application allows you to easily and quickly get information about given localisation. Application returns such information as: country, city, route/street, street number, lat and lng.
Home-page: UNKNOWN
Author: Sławomir Kabik
Author-email: slawek@redsoftware.pl
License: Copyright (c) 2014, Sławomir Kabik
